termdoc/__init__.py
termdoc/htdm.py
termdoc-0.3.dist-info/LICENSE
termdoc-0.3.dist-info/METADATA
termdoc-0.3.dist-info/WHEEL
termdoc-0.3.dist-info/top_level.txt
termdoc-0.3.dist-info/RECORD
