Metadata-Version: 2.1
Name: termdoc
Version: 0.3
Summary: Python library and tools for working with term-document matrices
Home-page: http://github.com/jtauber/termdoc
Author: James Tauber
Author-email: jtauber@jtauber.com
License: MIT
License-File: LICENSE
